{
  "reikai": {
    "entries": {
      "0000": [
        {
          "def": "<ruby><rb>見</rb><rt>み</rt></ruby>たりさわったりすることができるもの。<ruby><rb>品物</rb><rt>しなもの</rt></ruby>。",
          "hyouki": [
            "物質"
          ]
        }
      ],
      "0001": [
        {
          "def": "<ruby><rb>公害</rb><rt>こうがい</rt></ruby>をなくし、<ruby><rb>自然</rb><rt>しぜん</rt></ruby>を<ruby><rb>守</rb><rt>まも</rt></ruby>る<ruby><rb>仕事</rb><rt>しごと</rt></ruby>をする<ruby><rb>国</rb><rt>くに</rt></ruby>の<ruby><rb>役所</rb><rt>やくしょ</rt></ruby>。",
          "hyouki": [
            "環境省"
          ]
        }
      ],
      "0002": [
        {
          "def": "<ruby><rb>体</rb><rt>からだ</rt></ruby>や<ruby><rb>心</rb><rt>こころ</rt></ruby>に<ruby><rb>悪</rb><rt>わる</rt></ruby>いところがなく、<ruby><rb>元気</rb><rt>げんき</rt></ruby>なようす。",
          "hyouki": [
            "健康"
          ]
        },
        {
          "def": "<ruby><rb>体</rb><rt>からだ</rt></ruby>や<ruby><rb>心</rb><rt>こころ</rt></ruby>のぐあい。",
          "hyouki": [
            "健康"
          ]
        }
      ],
      "0003": [
        {
          "def": "<ruby><rb>液体</rb><rt>えきたい</rt></ruby>や<ruby><rb>気体</rb><rt>きたい</rt></ruby>のこい、うすいの<ruby><rb>度合</rb><rt>どあ</rt></ruby>い。",
          "hyouki": [
            "濃度"
          ]
        }
      ],
      "0004": [
        {
          "def": "<ruby><rb>多</rb><rt>おお</rt></ruby>い<ruby><rb>少</rb><rt>すく</rt></ruby>ないや<ruby><rb>高</rb><rt>たか</rt></ruby>い<ruby><rb>低</rb><rt>ひく</rt></ruby>いなどがないように、ならすこと。",
          "hyouki": [
            "平均"
          ]
        },
        {
          "def": "つり<ruby><rb>合</rb><rt>あ</rt></ruby>いがとれること。バランス。",
          "hyouki": [
            "平均"
          ]
        }
      ],
      "0005": [
        {
          "def": "ものごとを<ruby><rb>比</rb><rt>くら</rt></ruby>べるとき、そのもととなるよりどころ。<ruby><rb>標準</rb><rt>ひょうじゅん</rt></ruby>。",
          "hyouki": [
            "基準"
          ]
        }
      ],
      "0006": [
        {
          "def": "<ruby><rb>仕事</rb><rt>しごと</rt></ruby>のつごうで<ruby><rb>決</rb><rt>き</rt></ruby>めた<ruby><rb>一年</rb><rt>いちねん</rt></ruby>の<ruby><rb>期間</rb><rt>きかん</rt></ruby>。ふつう<ruby><rb>四月</rb><rt>しがつ</rt></ruby><ruby><rb>一日</rb><rt>ついたち</rt></ruby>に<ruby><rb>始</rb><rt>はじ</rt></ruby>まり、<ruby><rb>翌年</rb><rt>よくねん</rt></ruby>の<ruby><rb>三月三十一日</rb><rt>さんがつさんじゅういちにち</rt></ruby>に<ruby><rb>終</rb><rt>お</rt></ruby>わる。",
          "hyouki": [
            "年度"
          ]
        }
      ],
      "0007": [
        {
          "def": "<ruby><rb>日本</rb><rt>にっぽん</rt></ruby>の<ruby><rb>南西部</rb><rt>なんせいぶ</rt></ruby>にある<ruby><rb>地方</rb><rt>ちほう</rt></ruby>。<ruby><rb>福岡</rb><rt>ふくおか</rt></ruby>・<ruby><rb>佐賀</rb><rt>さが</rt></ruby>・<ruby><rb>長崎</rb><rt>ながさき</rt></ruby>・<ruby><rb>熊本</rb><rt>くまもと</rt></ruby>・<ruby><rb>大分</rb><rt>おおいた</rt></ruby>・<ruby><rb>宮崎</rb><rt>みやざき</rt></ruby>・<ruby><rb>鹿児島</rb><rt>かごしま</rt></ruby>・<ruby><rb>沖縄</rb><rt>おきなわ</rt></ruby>の八<ruby><rb>県</rb><rt>けん</rt></ruby>がある。",
          "hyouki": [
            "九州地方"
          ]
        }
      ]
    }
  }
}
